privex/__init__.py
privex/helpers/__init__.py
privex/helpers/asyncx.py
privex/helpers/black_magic.py
privex/helpers/collections.py
privex/helpers/common.py
privex/helpers/converters.py
privex/helpers/decorators.py
privex/helpers/django.py
privex/helpers/exceptions.py
privex/helpers/geoip.py
privex/helpers/mockers.py
privex/helpers/plugin.py
privex/helpers/settings.py
privex/helpers/thread.py
privex/helpers/types.py
privex/helpers/version.py
privex/helpers/cache/CacheAdapter.py
privex/helpers/cache/MemcachedCache.py
privex/helpers/cache/MemoryCache.py
privex/helpers/cache/RedisCache.py
privex/helpers/cache/SqliteCache.py
privex/helpers/cache/__init__.py
privex/helpers/cache/extras.py
privex/helpers/cache/post_deps.py
privex/helpers/cache/asyncx/AsyncMemcachedCache.py
privex/helpers/cache/asyncx/AsyncMemoryCache.py
privex/helpers/cache/asyncx/AsyncRedisCache.py
privex/helpers/cache/asyncx/AsyncSqliteCache.py
privex/helpers/cache/asyncx/__init__.py
privex/helpers/cache/asyncx/base.py
privex/helpers/crypto/EncryptHelper.py
privex/helpers/crypto/KeyManager.py
privex/helpers/crypto/__init__.py
privex/helpers/crypto/base.py
privex/helpers/extras/__init__.py
privex/helpers/extras/attrs.py
privex/helpers/extras/git.py
privex/helpers/net/__init__.py
privex/helpers/net/base.py
privex/helpers/net/common.py
privex/helpers/net/dns.py
privex/helpers/net/socket.py
privex/helpers/net/util.py
privex/helpers/setuppy/__init__.py
privex/helpers/setuppy/bump.py
privex/helpers/setuppy/commands.py
privex/helpers/setuppy/common.py
privex_helpers-3.3.0.dist-info/LICENSE
privex_helpers-3.3.0.dist-info/METADATA
privex_helpers-3.3.0.dist-info/WHEEL
privex_helpers-3.3.0.dist-info/top_level.txt
privex_helpers-3.3.0.dist-info/RECORD
