Metadata-Version: 2.1
Name: privex-helpers
Version: 3.3.0
Summary: A variety of helper functions and classes, useful for many different projects
Home-page: https://github.com/Privex/python-helpers
Author: Chris (Someguy123) @ Privex
Author-email: chris@privex.io
License: MIT
Platform: UNKNOWN
Classifier: Programming Language :: Python :: 3
Classifier: Programming Language :: Python :: 3.6
Classifier: Programming Language :: Python :: 3.7
Classifier: Programming Language :: Python :: 3.8
Classifier: License :: OSI Approved :: MIT License
Classifier: Operating System :: OS Independent
Requires-Dist: privex-loghelper (>=1.0.4)
Requires-Dist: python-dateutil
Requires-Dist: sniffio
Requires-Dist: async-property
Requires-Dist: attrs
Provides-Extra: cache
Requires-Dist: redis (>=3.3) ; extra == 'cache'
Requires-Dist: aioredis (>=1.3) ; extra == 'cache'
Requires-Dist: hiredis ; extra == 'cache'
Requires-Dist: pylibmc (>=1.6.0) ; extra == 'cache'
Requires-Dist: aiomcache (>=0.6) ; extra == 'cache'
Requires-Dist: privex-db (>=0.9.2) ; extra == 'cache'
Requires-Dist: aiosqlite (>=0.12) ; extra == 'cache'
Provides-Extra: crypto
Requires-Dist: cryptography (>=2.8) ; extra == 'crypto'
Provides-Extra: dev
Requires-Dist: redis (>=3.3) ; extra == 'dev'
Requires-Dist: aioredis (>=1.3) ; extra == 'dev'
Requires-Dist: hiredis ; extra == 'dev'
Requires-Dist: pylibmc (>=1.6.0) ; extra == 'dev'
Requires-Dist: aiomcache (>=0.6) ; extra == 'dev'
Requires-Dist: privex-db (>=0.9.2) ; extra == 'dev'
Requires-Dist: aiosqlite (>=0.12) ; extra == 'dev'
Requires-Dist: dnspython (>=1.16) ; extra == 'dev'
Requires-Dist: geoip2 (>=3.0.0) ; extra == 'dev'
Requires-Dist: attrs ; extra == 'dev'
Requires-Dist: cryptography (>=2.8) ; extra == 'dev'
Requires-Dist: setuptools ; extra == 'dev'
Requires-Dist: wheel ; extra == 'dev'
Requires-Dist: twine ; extra == 'dev'
Requires-Dist: semver ; extra == 'dev'
Requires-Dist: Django ; extra == 'dev'
Requires-Dist: Sphinx (>=3.1.1) ; extra == 'dev'
Requires-Dist: sphinx-autobuild (>=0.7.1) ; extra == 'dev'
Requires-Dist: restructuredtext-lint (>=1.3.0) ; extra == 'dev'
Requires-Dist: sphinx-rtd-theme (>=0.5.0) ; extra == 'dev'
Requires-Dist: MarkupSafe (>=1.1.1) ; extra == 'dev'
Requires-Dist: docutils (>=0.14) ; extra == 'dev'
Requires-Dist: pytest (==5.4.*) ; extra == 'dev'
Requires-Dist: pytest-cov ; extra == 'dev'
Requires-Dist: pytest-asyncio (==0.14.*) ; extra == 'dev'
Requires-Dist: coverage ; extra == 'dev'
Requires-Dist: codecov ; extra == 'dev'
Requires-Dist: mypy (>=0.780) ; extra == 'dev'
Requires-Dist: jupyter ; extra == 'dev'
Provides-Extra: dev_general
Requires-Dist: mypy (>=0.780) ; extra == 'dev_general'
Requires-Dist: jupyter ; extra == 'dev_general'
Provides-Extra: django
Requires-Dist: Django ; extra == 'django'
Provides-Extra: docs
Requires-Dist: Sphinx (>=3.1.1) ; extra == 'docs'
Requires-Dist: sphinx-autobuild (>=0.7.1) ; extra == 'docs'
Requires-Dist: restructuredtext-lint (>=1.3.0) ; extra == 'docs'
Requires-Dist: sphinx-rtd-theme (>=0.5.0) ; extra == 'docs'
Requires-Dist: MarkupSafe (>=1.1.1) ; extra == 'docs'
Requires-Dist: docutils (>=0.14) ; extra == 'docs'
Provides-Extra: extras
Requires-Dist: attrs ; extra == 'extras'
Provides-Extra: full
Requires-Dist: redis (>=3.3) ; extra == 'full'
Requires-Dist: aioredis (>=1.3) ; extra == 'full'
Requires-Dist: hiredis ; extra == 'full'
Requires-Dist: pylibmc (>=1.6.0) ; extra == 'full'
Requires-Dist: aiomcache (>=0.6) ; extra == 'full'
Requires-Dist: privex-db (>=0.9.2) ; extra == 'full'
Requires-Dist: aiosqlite (>=0.12) ; extra == 'full'
Requires-Dist: dnspython (>=1.16) ; extra == 'full'
Requires-Dist: geoip2 (>=3.0.0) ; extra == 'full'
Requires-Dist: attrs ; extra == 'full'
Requires-Dist: cryptography (>=2.8) ; extra == 'full'
Requires-Dist: setuptools ; extra == 'full'
Requires-Dist: wheel ; extra == 'full'
Requires-Dist: twine ; extra == 'full'
Requires-Dist: semver ; extra == 'full'
Provides-Extra: geoip
Requires-Dist: geoip2 (>=3.0.0) ; extra == 'geoip'
Requires-Dist: attrs ; extra == 'geoip'
Provides-Extra: net
Requires-Dist: dnspython (>=1.16) ; extra == 'net'
Requires-Dist: geoip2 (>=3.0.0) ; extra == 'net'
Requires-Dist: attrs ; extra == 'net'
Provides-Extra: setuppy
Requires-Dist: setuptools ; extra == 'setuppy'
Requires-Dist: wheel ; extra == 'setuppy'
Requires-Dist: twine ; extra == 'setuppy'
Requires-Dist: semver ; extra == 'setuppy'
Provides-Extra: tests
Requires-Dist: pytest (==5.4.*) ; extra == 'tests'
Requires-Dist: pytest-cov ; extra == 'tests'
Requires-Dist: pytest-asyncio (==0.14.*) ; extra == 'tests'
Requires-Dist: coverage ; extra == 'tests'
Requires-Dist: codecov ; extra == 'tests'
